zedline/__init__.py
zedline/core.py
zedline-2.0.0.dist-info/licenses/LICENSE
zedline-2.0.0.dist-info/METADATA
zedline-2.0.0.dist-info/WHEEL
zedline-2.0.0.dist-info/top_level.txt
zedline-2.0.0.dist-info/RECORD
