Metadata-Version: 2.4
Name: zedline
Version: 2.0.0
Summary: ZedLine: The first Iranian free web service toolkit for developers
Home-page: https://zedline.ir
Author: ZedLine Co.
Author-email: no-reply@zedline.ir
Classifier: Programming Language :: Python :: 3
Classifier: License :: OSI Approved :: MIT License
Classifier: Operating System :: OS Independent
Requires-Python: >=3.7
License-File: LICENSE
Dynamic: author
Dynamic: author-email
Dynamic: classifier
Dynamic: description
Dynamic: description-content-type
Dynamic: home-page
Dynamic: license-file
Dynamic: requires-python
Dynamic: summary
